octopy_admin/__init__.py
octopy_admin/graph/__init__.py
octopy_admin/graph/gql_files/create-branch-protection-rule.gql
octopy_admin/graph/gql_files/create-enterprise-org.gql
octopy_admin/graph/gql_files/create-repository.gql
octopy_admin/graph/gql_files/get-enterprise-admins.gql
octopy_admin/graph/gql_files/get-enterprise-id.gql
octopy_admin/graph/gql_files/get-enterprise-members.gql
octopy_admin/graph/gql_files/get-enterprise-orgs.gql
octopy_admin/graph/gql_files/get-org-members-with-role.gql
octopy_admin/graph/gql_files/get-org-repos.gql
octopy_admin/graph/gql_files/get-repo-branch-protection-rules.gql
octopy_admin/graph/gql_files/get-repo-collaborators-with-permission.gql
octopy_admin/graph/gql_files/get-repo-id.gql
octopy_admin/graph/gql_files/get-repo-languages.gql
octopy_admin/graph/gql_files/get-repo-pr-review-requested-events.gql
octopy_admin/graph/gql_files/get-repo-prs.gql
octopy_admin/graph/gql_files/get-the-authenticated-user.gql
octopy_admin/graph/gql_files/get-users-public-repos.gql
octopy_admin/graph/graph_client.py
octopy_admin/graph/graph_mutation.py
octopy_admin/graph/graph_query.py
octopy_admin/rest/__init__.py
octopy_admin/rest/apis/__init__.py
octopy_admin/rest/apis/actions/__init__.py
octopy_admin/rest/apis/actions/actions.py
octopy_admin/rest/apis/activity/__init__.py
octopy_admin/rest/apis/activity/activity.py
octopy_admin/rest/apis/apps/__init__.py
octopy_admin/rest/apis/apps/apps.py
octopy_admin/rest/apis/billing/__init__.py
octopy_admin/rest/apis/billing/billing.py
octopy_admin/rest/apis/checks/__init__.py
octopy_admin/rest/apis/checks/checks.py
octopy_admin/rest/apis/code_scanning/__init__.py
octopy_admin/rest/apis/code_scanning/code_scanning.py
octopy_admin/rest/apis/codes_of_conduct/__init__.py
octopy_admin/rest/apis/codes_of_conduct/codes_of_conduct.py
octopy_admin/rest/apis/codespaces/__init__.py
octopy_admin/rest/apis/codespaces/codespaces.py
octopy_admin/rest/apis/dependabot/__init__.py
octopy_admin-0.2.9.dist-info/LICENSE
octopy_admin-0.2.9.dist-info/WHEEL
octopy_admin-0.2.9.dist-info/METADATA
octopy_admin-0.2.9.dist-info/RECORD
